{"299":{"id":"299","Name":"RadioSelectThreshold","FeatureGroup":"Collecting","DefaultValue":"60","Explanation":"","Priority":"0"},"300":{"id":"300","Name":"CollectingPosn","FeatureGroup":"Collecting","DefaultValue":"4","Explanation":"","Priority":"0"},"301":{"id":"301","Name":"ContractType","FeatureGroup":"Contracts","DefaultValue":"","Explanation":"","Priority":"0"},"302":{"id":"302","Name":"DefaultReportPoint","FeatureGroup":"Contracts","DefaultValue":"0","Explanation":"Where to report to 0=Not set, set to venue number to include in contracts","Priority":"0"},"303":{"id":"303","Name":"PayByCheque","FeatureGroup":"Contracts","DefaultValue":"0","Explanation":"0 \u2013 NO, 1 \u2013 Yes, 2- Last Year","Priority":"0"},"304":{"id":"304","Name":"PublicLiability","FeatureGroup":"Contracts","DefaultValue":"","Explanation":"If set requires Insurance upload by performers","Priority":"0"},"305":{"id":"305","Name":"CSSColourMain","FeatureGroup":"CSS","DefaultValue":"#fcb900","Explanation":"Main Festival Colour","Priority":"10"},"306":{"id":"306","Name":"CSSColourDark","FeatureGroup":"CSS","DefaultValue":"#993300","Explanation":"Main Dark Contrast eg for links","Priority":"9"},"307":{"id":"307","Name":"CSSColourContrast","FeatureGroup":"CSS","DefaultValue":"#1a0000","Explanation":"","Priority":"9"},"308":{"id":"308","Name":"CSSColourHeader","FeatureGroup":"CSS","DefaultValue":"#404040","Explanation":"","Priority":"0"},"309":{"id":"309","Name":"CSSColourMainLink","FeatureGroup":"CSS","DefaultValue":"#b32d00","Explanation":"","Priority":"0"},"310":{"id":"310","Name":"CSSColourDonate","FeatureGroup":"CSS","DefaultValue":"#e67300","Explanation":"","Priority":"0"},"311":{"id":"311","Name":"CSSColourDropdown","FeatureGroup":"CSS","DefaultValue":"#f0f0f0","Explanation":"","Priority":"0"},"312":{"id":"312","Name":"CSSColourNavButton","FeatureGroup":"CSS","DefaultValue":"#a30046","Explanation":"","Priority":"0"},"313":{"id":"313","Name":"CSSColourTue, Wed, Thur, Fri, Sat, Sun, Mon","FeatureGroup":"CSS","DefaultValue":"Slategray, seagreen, darkcyan,Slategray, seagreen, darkcyan,peru","Explanation":"Colours used for each day of programme","Priority":"0"},"314":{"id":"314","Name":"CSSColourDayTabBack","FeatureGroup":"CSS","DefaultValue":"#f4f4f4","Explanation":"Used as the background for Day tables (above)","Priority":"0"},"315":{"id":"315","Name":"CSSColourArtTitle","FeatureGroup":"CSS","DefaultValue":"#005C8F","Explanation":"Default Article Title Colour","Priority":"0"},"316":{"id":"316","Name":"CSSColourTicket","FeatureGroup":"CSS","DefaultValue":"#CF1F84","Explanation":"Ticket hover colour","Priority":"0"},"317":{"id":"317","Name":"CSSColourPrivate","FeatureGroup":"CSS","DefaultValue":"#fff0b3","Explanation":"Staff Header background","Priority":"0"},"318":{"id":"318","Name":"FooterBack","FeatureGroup":"CSS","DefaultValue":"","Explanation":"Background to the footer, can be colour or an image","Priority":"0"},"319":{"id":"319","Name":"Procession","FeatureGroup":"Dance","DefaultValue":"Procession","Explanation":"If you want to call it a Parade, set to Parade","Priority":"0"},"320":{"id":"320","Name":"MultiLimFri (Sat, Sun ...","FeatureGroup":"Dance","DefaultValue":"","Explanation":"Limit dance sides to that number on that day (work in progress)","Priority":"0"},"321":{"id":"321","Name":"ProcessDays","FeatureGroup":"Dance","DefaultValue":"","Explanation":"Bit map of days with processions bit 1=Fri, 2=Sat, 4=Sun, 8 = Mon","Priority":"0"},"322":{"id":"322","Name":"DanceNeedAddress","FeatureGroup":"Dance","DefaultValue":"","Explanation":"Is the Address a Needed field","Priority":"0"},"323":{"id":"323","Name":"DanceOrg","FeatureGroup":"Dance","DefaultValue":"","Explanation":"Dance Organiser(s) to sign off dance emails","Priority":"0"},"324":{"id":"324","Name":"DanceDefaultSlot","FeatureGroup":"Dance","DefaultValue":"30","Explanation":"Sub Event default size for dance","Priority":"0"},"325":{"id":"325","Name":"EmailButtons","FeatureGroup":"Dance","DefaultValue":"Dance","Explanation":"?","Priority":"0"},"326":{"id":"326","Name":"SpecialInvite","FeatureGroup":"Dance","DefaultValue":"","Explanation":"?","Priority":"0"},"327":{"id":"327","Name":"DanceComp","FeatureGroup":"Dance","DefaultValue":"","Explanation":"Enables a dance competition","Priority":"0"},"328":{"id":"328","Name":"EmailButtons","FeatureGroup":"Dance","DefaultValue":"","Explanation":"Enable Email Buttons Feature ","Priority":"0"},"329":{"id":"329","Name":"DanceNeedInsurance","FeatureGroup":"Dance","DefaultValue":"","Explanation":"If set insurance is checked","Priority":"0"},"330":{"id":"330","Name":"DanceNeedPerformers","FeatureGroup":"Dance","DefaultValue":"","Explanation":"If set Number of performers is checked","Priority":"0"},"331":{"id":"331","Name":"DanceNeedMobile","FeatureGroup":"Dance","DefaultValue":"","Explanation":"If set need a Mobile number","Priority":"0"},"332":{"id":"332","Name":"DanceNeedDays","FeatureGroup":"Dance","DefaultValue":"","Explanation":"If set need to select at least one day","Priority":"0"},"333":{"id":"333","Name":"DanceSpecialMessage","FeatureGroup":"Dance","DefaultValue":"","Explanation":"Enables a special message for Dance sides. Value: Messages Name","Priority":"0"},"334":{"id":"334","Name":"DanceDefaultPerSlot","FeatureGroup":"Dance","DefaultValue":"2","Explanation":"Sides per sub event slot default","Priority":"0"},"335":{"id":"335","Name":"AllDanceTimes","FeatureGroup":"Dance","DefaultValue":"","Explanation":"If set always shows the times for each dance slot.  Not normally needed","Priority":"0"},"336":{"id":"336","Name":"RestrictOneProcession","FeatureGroup":"Dance","DefaultValue":"","Explanation":"If set, dance sides can only indicate one of the processions","Priority":"0"},"337":{"id":"337","Name":"DanceEmailsFrom","FeatureGroup":"Dance","DefaultValue":"Dance@Feature('HostURL')","Explanation":"Email address Dance emails will have","Priority":"0"},"448":{"id":"448","Name":"DanceFullFri, Sat, Sun, Mon","FeatureGroup":"Dance","DefaultValue":"","Explanation":"If Set that day is full (Short term hack until day limits coded properly)","Priority":"0"},"338":{"id":"338","Name":"SMTPuser","FeatureGroup":"Email","DefaultValue":"","Explanation":"Username for sending emails (internal never externally seen)","Priority":"0"},"339":{"id":"339","Name":"SMTPpwd","FeatureGroup":"Email","DefaultValue":"","Explanation":"Password for SMTPuser","Priority":"0"},"340":{"id":"340","Name":"SMPTserver","FeatureGroup":"Email","DefaultValue":"Feature('HostURL')","Explanation":"Server to send email from (if sending via another server)","Priority":"0"},"341":{"id":"341","Name":"SMTPsubdomain","FeatureGroup":"Email","DefaultValue":"","Explanation":"To add a subdomain to the mail address","Priority":"0"},"342":{"id":"342","Name":"EmailFromAllowed","FeatureGroup":"Email","DefaultValue":"","Explanation":"","Priority":"0"},"343":{"id":"343","Name":"EmailReplyTo","FeatureGroup":"Email","DefaultValue":"","Explanation":"","Priority":"0"},"344":{"id":"344","Name":"ShowYear","FeatureGroup":"Festival","DefaultValue":"","Explanation":"Festival to show on public pages","Priority":"100"},"345":{"id":"345","Name":"PlanYear","FeatureGroup":"Festival","DefaultValue":"","Explanation":"Festival to show on staff pages","Priority":"100"},"346":{"id":"346","Name":"ShortName","FeatureGroup":"Festival","DefaultValue":"","Explanation":"Short acronym for festival \u2013 must be set","Priority":"0"},"347":{"id":"347","Name":"FestLegalName","FeatureGroup":"Festival","DefaultValue":"","Explanation":"Legal name of the festival eg Chippenham Folk Festival C.I.C.","Priority":"0"},"348":{"id":"348","Name":"FestLegalAddr[]","FeatureGroup":"Festival","DefaultValue":"","Explanation":"The formal address of the festival, have as entries for each line of the address as needed","Priority":"0"},"349":{"id":"349","Name":"FestPhone","FeatureGroup":"Festival","DefaultValue":"","Explanation":"Phone number (for legal documents)","Priority":"0"},"350":{"id":"350","Name":"FestContractEmail","FeatureGroup":"Festival","DefaultValue":"","Explanation":"? (Contracts)","Priority":"0"},"351":{"id":"351","Name":"FestName","FeatureGroup":"Festival","DefaultValue":"","Explanation":"Name of Festival e.g. Chippenham Folk Festival ","Priority":"0"},"352":{"id":"352","Name":"HostURL","FeatureGroup":"Festival","DefaultValue":"","Explanation":"URL for the festival eg chippfolk.co.uk","Priority":"0"},"353":{"id":"353","Name":"FestHomeName","FeatureGroup":"Festival","DefaultValue":"","Explanation":"Name of the festival\u2019s location \u2013 eg Chippenham","Priority":"0"},"354":{"id":"354","Name":"EnableDateChange","FeatureGroup":"Festival","DefaultValue":"","Explanation":"If you have to change date of festival, this enables the messages","Priority":"0"},"355":{"id":"355","Name":"EnableCancelMsg","FeatureGroup":"Festival","DefaultValue":"","Explanation":"Message to be used on a date change","Priority":"0"},"356":{"id":"356","Name":"FestCompanyNumber","FeatureGroup":"Festival","DefaultValue":"","Explanation":"Company Number (if any)","Priority":"0"},"357":{"id":"357","Name":"RealFaviconGeneratorKey","FeatureGroup":"Festival","DefaultValue":"","Explanation":"API Key used with Real Favicon Generator ","Priority":"0"},"358":{"id":"358","Name":"LookBackYears","FeatureGroup":"Festival","DefaultValue":"1","Explanation":"Number of years to simply look back","Priority":"0"},"359":{"id":"359","Name":"Camping","FeatureGroup":"Festival","DefaultValue":"","Explanation":"See YearData.php to work out what it does","Priority":"0"},"360":{"id":"360","Name":"FestVatNumber","FeatureGroup":"Finance","DefaultValue":"","Explanation":"Vat number, if set the festival charges VAT","Priority":"0"},"361":{"id":"361","Name":"VatRate","FeatureGroup":"Finance","DefaultValue":"","Explanation":"VAT %age to use (if festival has a VAT Number","Priority":"0"},"362":{"id":"362","Name":"FestBankAdr","FeatureGroup":"Finance","DefaultValue":"","Explanation":"Address of festivals bank","Priority":"0"},"363":{"id":"363","Name":"FestBankSortCode","FeatureGroup":"Finance","DefaultValue":"","Explanation":"Bank Sort Code","Priority":"0"},"364":{"id":"364","Name":"FestBankAccountNum","FeatureGroup":"Finance","DefaultValue":"","Explanation":"Bank Account Number","Priority":"0"},"365":{"id":"365","Name":"InvoiceLogo","FeatureGroup":"Finance","DefaultValue":"images\/icons\/Long-Banner-Logo.png","Explanation":"Logo to be used on invoices","Priority":"0"},"366":{"id":"366","Name":"FestTresEmail","FeatureGroup":"Finance","DefaultValue":"Treasurer@Feature('HostURL'","Explanation":"Email address Finance emails come from","Priority":"0"},"367":{"id":"367","Name":"DefaultColumns","FeatureGroup":"Layout","DefaultValue":"4","Explanation":"Default columns for Articles (front page)","Priority":"0"},"368":{"id":"368","Name":"PerformerBanners","FeatureGroup":"Layout","DefaultValue":"","Explanation":"If set, system will attempt making a banner for each side at the top of their performer public page.   ","Priority":"0"},"369":{"id":"369","Name":"TopText4Perfs","FeatureGroup":"Layout","DefaultValue":"","Explanation":"If set, the short performers description is added to a @Perf xxx tile on the front page","Priority":"0"},"370":{"id":"370","Name":"DefaultPageBanner","FeatureGroup":"Layout","DefaultValue":"","Explanation":"Default Banner for top of pages","Priority":"0"},"371":{"id":"371","Name":"TopBannerScrollRate","FeatureGroup":"Layout","DefaultValue":"2000","Explanation":"Scroll rate of top banner on top page (in milliseconds)","Priority":"0"},"372":{"id":"372","Name":"BannerOverlay","FeatureGroup":"Layout","DefaultValue":"","Explanation":"If set allows text over the banner on top page","Priority":"0"},"373":{"id":"373","Name":"SponsorTime","FeatureGroup":"Layout","DefaultValue":"2000","Explanation":"Change rate of sponsors","Priority":"0"},"374":{"id":"374","Name":"FoodCenter","FeatureGroup":"Layout","DefaultValue":"","Explanation":"Feature number to use a the food map centre","Priority":"0"},"375":{"id":"375","Name":"LinupShortDesc_Dance, _Music, _Comedy, _Family, _Youth, _Ceilidh, _Other","FeatureGroup":"Layout","DefaultValue":"","Explanation":"If set show the short description of the performer on the lineup pages","Priority":"0"},"376":{"id":"376","Name":"PrevRealFest","FeatureGroup":"Layout","DefaultValue":"Yeardata[\u2018PrevFest\u2019]","Explanation":"Allows override of \u201cPrevious Festival\u201d ","Priority":"0"},"377":{"id":"377","Name":"NoEventsPost","FeatureGroup":"Layout","DefaultValue":"please check back later","Explanation":"Words to apply when a programme event category is not yet public","Priority":"0"},"378":{"id":"378","Name":"NotAllPublic","FeatureGroup":"Layout","DefaultValue":"","Explanation":"Enables \u201cThese venues have published events, more are coming\u201d on venue list","Priority":"0"},"379":{"id":"379","Name":"MainMenuTable","FeatureGroup":"Layout","DefaultValue":"","Explanation":"Enables menu from database (should be always 1 now)","Priority":"0"},"380":{"id":"380","Name":"Facebook","FeatureGroup":"Layout","DefaultValue":"**NONE**","Explanation":"Address to append to http:\/\/facebook.com\/ in icon bar","Priority":"0"},"381":{"id":"381","Name":"Twitter","FeatureGroup":"Layout","DefaultValue":"**NONE**","Explanation":"Address to append to http:\/\/X.com\/ in icon bar","Priority":"0"},"382":{"id":"382","Name":"Instagram","FeatureGroup":"Layout","DefaultValue":"**NONE**","Explanation":"Address to append to http:\/\/instagram.com\/ in icon bar","Priority":"0"},"383":{"id":"383","Name":"YouTube","FeatureGroup":"Layout","DefaultValue":"**NONE**","Explanation":"Address to append to http:\/\/YouTube.com\/ in icon bar","Priority":"0"},"384":{"id":"384","Name":"Donate","FeatureGroup":"Layout","DefaultValue":"","Explanation":"Enables Donate Button","Priority":"0"},"385":{"id":"385","Name":"WebsiteBanner2","FeatureGroup":"Layout","DefaultValue":"","Explanation":"header-logo head-white-logo","Priority":"0"},"386":{"id":"386","Name":"WebsiteBanner","FeatureGroup":"Layout","DefaultValue":"","Explanation":"header-logo head-coloured-logo","Priority":"0"},"387":{"id":"387","Name":"DefaultDirLat","FeatureGroup":"Maps","DefaultValue":"Feature('MapLat')","Explanation":"Default Lat to give directions from ","Priority":"0"},"388":{"id":"388","Name":"DefaultDirLong","FeatureGroup":"Maps","DefaultValue":"Feature('MapLong')","Explanation":"Default Long to give directions from","Priority":"0"},"389":{"id":"389","Name":"MapLat","FeatureGroup":"Maps","DefaultValue":"","Explanation":"Centre location for Google map","Priority":"0"},"390":{"id":"390","Name":"MapLong","FeatureGroup":"Maps","DefaultValue":"","Explanation":"Centre Location for Google map","Priority":"0"},"391":{"id":"391","Name":"GoogleAPI","FeatureGroup":"Maps","DefaultValue":"","Explanation":"API used when getting directions from Google","Priority":"0"},"392":{"id":"392","Name":"DirectionDefault","FeatureGroup":"Maps","DefaultValue":"","Explanation":"Name of location where default directions are from","Priority":"0"},"393":{"id":"393","Name":"MapStartZoom","FeatureGroup":"Maps","DefaultValue":"17","Explanation":"Starting Zoom level","Priority":"0"},"394":{"id":"394","Name":"SpecialMessage","FeatureGroup":"Music","DefaultValue":"","Explanation":"Enables a special message for non Dance sides. Value: Messages Name","Priority":"0"},"395":{"id":"395","Name":"MusicTypes","FeatureGroup":"Music","DefaultValue":"","Explanation":"Enables the Type field for non-dance performers","Priority":"0"},"396":{"id":"396","Name":"NeedShortBlurb","FeatureGroup":"Music","DefaultValue":"","Explanation":"Is a short blurb needed","Priority":"0"},"397":{"id":"397","Name":"NeedPhoto","FeatureGroup":"Music","DefaultValue":"","Explanation":"Is a Photo needed","Priority":"0"},"398":{"id":"398","Name":"MusicDefaultPerSlot","FeatureGroup":"Music","DefaultValue":"1","Explanation":"Performers per sub event slot default (not currently used)","Priority":"0"},"399":{"id":"399","Name":"NeedBandMembers","FeatureGroup":"Music","DefaultValue":"","Explanation":"Ask for band members for music performers","Priority":"0"},"400":{"id":"400","Name":"PerformerAvail","FeatureGroup":"Music","DefaultValue":"","Explanation":"Ask for availability","Priority":"0"},"401":{"id":"401","Name":"MusicWristBands","FeatureGroup":"Music","DefaultValue":"","Explanation":"?","Priority":"0"},"402":{"id":"402","Name":"PerformerTickets","FeatureGroup":"Performer","DefaultValue":"","Explanation":"How to handle them: Wimb, Chip (needs explaining)","Priority":"0"},"403":{"id":"403","Name":"CampControl","FeatureGroup":"Performers","DefaultValue":"","Explanation":"?","Priority":"0"},"404":{"id":"404","Name":"RecordEventChanges","FeatureGroup":"Publicity","DefaultValue":"","Explanation":"Record Event changes to report programme differences","Priority":"0"},"405":{"id":"405","Name":"RecordPerfChanges","FeatureGroup":"Publicity","DefaultValue":"","Explanation":"Record Performer changes to report programme differences","Priority":"0"},"406":{"id":"406","Name":"FreeText","FeatureGroup":"Publicity","DefaultValue":"Free","Explanation":"Free, Donation, what word(s) to add to an event without a price","Priority":"0"},"407":{"id":"407","Name":"SeasonName","FeatureGroup":"Publicity","DefaultValue":"Weekend Ticket","Explanation":"Name of a full ticket","Priority":"0"},"408":{"id":"408","Name":"MailListMgrEmail","FeatureGroup":"Publicity","DefaultValue":"","Explanation":"Who to send emails about the mailing list to","Priority":"0"},"409":{"id":"409","Name":"MailListID","FeatureGroup":"Publicity","DefaultValue":"","Explanation":"Mailing List ID as used by Octopus email","Priority":"0"},"410":{"id":"410","Name":"PerformerPairsExtra","FeatureGroup":"Publicity","DefaultValue":"7","Explanation":"Default pairs of performers per page","Priority":"0"},"411":{"id":"411","Name":"OmitEmptyDescriptions","FeatureGroup":"Publicity","DefaultValue":"","Explanation":"If set Performers without descriptions will be omitted","Priority":"0"},"412":{"id":"412","Name":"PaperColouredEvents","FeatureGroup":"Publicity","DefaultValue":"","Explanation":"Use Day Colours in printed programme","Priority":"0"},"413":{"id":"413","Name":"PaperEventFont","FeatureGroup":"Publicity","DefaultValue":"12","Explanation":"Font size for printed programme","Priority":"0"},"414":{"id":"414","Name":"WebSiteBanner","FeatureGroup":"Publicity","DefaultValue":"","Explanation":"Banner at the top of Publicity posters","Priority":"0"},"415":{"id":"415","Name":"Testing","FeatureGroup":"Testing","DefaultValue":"","Explanation":"Dev use only","Priority":"0"},"416":{"id":"416","Name":"TradeEmail","FeatureGroup":"Trade","DefaultValue":"Trade@Feature('HostURL')","Explanation":"Email address Trade emails should come from","Priority":"0"},"417":{"id":"417","Name":"TradeLastWeek","FeatureGroup":"Trade","DefaultValue":"14","Explanation":"Days after sending a quote before showing the \u201cLast week message\u201d","Priority":"0"},"418":{"id":"418","Name":"TradeUnQuote","FeatureGroup":"Trade","DefaultValue":"14","Explanation":"Days after sending last week, before showing \u201cUnQuote Message\u201d","Priority":"0"},"419":{"id":"419","Name":"TradeDateChange","FeatureGroup":"Trade","DefaultValue":"","Explanation":"","Priority":"0"},"420":{"id":"420","Name":"TradePower","FeatureGroup":"Trade","DefaultValue":"","Explanation":"Enable Power for traders","Priority":"0"},"421":{"id":"421","Name":"InviteBetter","FeatureGroup":"Trade","DefaultValue":"","Explanation":"Enables the \u201cInvite Better\u201d Message for Trade","Priority":"0"},"422":{"id":"422","Name":"TableCost","FeatureGroup":"Trade","DefaultValue":"","Explanation":"Cost of a table","Priority":"0"},"423":{"id":"423","Name":"DefaultPitch","FeatureGroup":"Trade","DefaultValue":"3Mx3M","Explanation":"","Priority":"0"},"424":{"id":"424","Name":"TradeBID","FeatureGroup":"Trade","DefaultValue":"","Explanation":"Show BID Tick box","Priority":"0"},"425":{"id":"425","Name":"TradeChamberCommerce","FeatureGroup":"Trade","DefaultValue":"","Explanation":"Show Chamber of Commerce Tick Box","Priority":"0"},"426":{"id":"426","Name":"NeedSageCode","FeatureGroup":"Trade","DefaultValue":"","Explanation":"Switch on Sage Codes","Priority":"0"},"427":{"id":"427","Name":"TradeDays","FeatureGroup":"Trade","DefaultValue":"","Explanation":"Ask Which days to trade","Priority":"0"},"428":{"id":"428","Name":"TradeExtras","FeatureGroup":"Trade","DefaultValue":"","Explanation":"Are their Trade Extras (power, tables etc)","Priority":"0"},"429":{"id":"429","Name":"TradeInvoicePay","FeatureGroup":"Trade","DefaultValue":"","Explanation":"0 = Invoices, 1 = Pay codes (avoid if possible)","Priority":"0"},"430":{"id":"430","Name":"TraderPasses","FeatureGroup":"Trade","DefaultValue":"","Explanation":"Ask number of Trader Passes wanted","Priority":"0"},"431":{"id":"431","Name":"TradeCarpark","FeatureGroup":"Trade","DefaultValue":"","Explanation":"Ask number of Car park passes needed","Priority":"0"},"432":{"id":"432","Name":"TradeCamping","FeatureGroup":"Trade","DefaultValue":"","Explanation":"Ask about camping","Priority":"0"},"433":{"id":"433","Name":"PaymentTerms","FeatureGroup":"Trade","DefaultValue":"30","Explanation":"Days to pay an invoice","Priority":"0"},"434":{"id":"434","Name":"TradeOrg","FeatureGroup":"Trade","DefaultValue":"","Explanation":"Name(s) of who is organising trade","Priority":"0"},"435":{"id":"435","Name":"CopyTradeEmailsTo","FeatureGroup":"Trade","DefaultValue":"","Explanation":"Copy all out going trade emails to this address as a bcc","Priority":"0"},"436":{"id":"436","Name":"SendTradeEmailFrom","FeatureGroup":"Trade","DefaultValue":"Trade@Feature('HostURL')","Explanation":"","Priority":"0"},"437":{"id":"437","Name":"LogAllTrade","FeatureGroup":"Trade","DefaultValue":"","Explanation":"If set all Trade is heavily logged ","Priority":"0"},"438":{"id":"438","Name":"AutoInvoices","FeatureGroup":"Trade","DefaultValue":"","Explanation":"If set it automatically sends invoices (normal state)","Priority":"0"},"439":{"id":"439","Name":"TradeStatus","FeatureGroup":"Trade","DefaultValue":"1","Explanation":"?","Priority":"0"},"440":{"id":"440","Name":"TradeBooking","FeatureGroup":"Trade","DefaultValue":"","Explanation":"?","Priority":"0"},"441":{"id":"441","Name":"TradeArtisan","FeatureGroup":"Trade","DefaultValue":"","Explanation":"If set enable separate Artisan messages","Priority":"0"},"442":{"id":"442","Name":"TradeLocLinks","FeatureGroup":"Trade","DefaultValue":"","Explanation":"?","Priority":"0"},"443":{"id":"443","Name":"TradeBaseMap","FeatureGroup":"Trade","DefaultValue":"","Explanation":"?","Priority":"0"},"444":{"id":"444","Name":"VolMoney","FeatureGroup":"Volunteers","DefaultValue":"","Explanation":"If set show tick box","Priority":"0"},"445":{"id":"445","Name":"VolPhoto","FeatureGroup":"Volunteers","DefaultValue":"","Explanation":"If show ask for Photo","Priority":"0"},"446":{"id":"446","Name":"VolDBS","FeatureGroup":"Volunteers","DefaultValue":"","Explanation":"If set ask about DBS","Priority":"0"},"447":{"id":"447","Name":"Vol_Camping","FeatureGroup":"Volunteers","DefaultValue":"","Explanation":"If set ask about camping","Priority":"0"}}